geomapfm/__init__.py
geomapfm/geomapfm.py
geomapfm-0.0.2.dist-info/LICENSE
geomapfm-0.0.2.dist-info/METADATA
geomapfm-0.0.2.dist-info/WHEEL
geomapfm-0.0.2.dist-info/top_level.txt
geomapfm-0.0.2.dist-info/RECORD
