Metadata-Version: 2.1
Name: geomapfm
Version: 0.0.2
Summary: Mapping application
Home-page: https://github.com/faraigit/geomapfm
Author: Farai Maxwell Marumbwa
Author-email: faraimax@gmail.com
License: MIT license
Keywords: geomapfm
Platform: UNKNOWN
Classifier: Development Status :: 2 - Pre-Alpha
Classifier: Intended Audience :: Developers
Classifier: License :: OSI Approved :: MIT License
Classifier: Natural Language :: English
Classifier: Programming Language :: Python :: 3
Classifier: Programming Language :: Python :: 3.5
Classifier: Programming Language :: Python :: 3.6
Classifier: Programming Language :: Python :: 3.7
Classifier: Programming Language :: Python :: 3.8
Requires-Python: >=3.5
